inframind.py
inframind-2.1.1.dist-info/licenses/LICENSE
inframind-2.1.1.dist-info/METADATA
inframind-2.1.1.dist-info/WHEEL
inframind-2.1.1.dist-info/entry_points.txt
inframind-2.1.1.dist-info/top_level.txt
inframind-2.1.1.dist-info/RECORD
