Metadata-Version: 2.4
Name: InfraMind
Version: 2.1.1
Summary: CLI tool for InfraMind CI/CD optimization engine
Home-page: https://github.com/IdanG7/InfraMind
Author: InfraMind Team
Author-email: InfraMind Team <hello@inframind.dev>
License: MIT
Project-URL: Homepage, https://github.com/IdanG7/InfraMind
Project-URL: Documentation, https://github.com/IdanG7/InfraMind/blob/main/docs/
Project-URL: Repository, https://github.com/IdanG7/InfraMind
Project-URL: Bug Tracker, https://github.com/IdanG7/InfraMind/issues
Project-URL: Changelog, https://github.com/IdanG7/InfraMind/releases
Keywords: ci-cd,optimization,machine-learning,devops,jenkins,github-actions,gitlab-ci,build-optimization
Platform: any
Classifier: Development Status :: 4 - Beta
Classifier: Intended Audience :: Developers
Classifier: Topic :: Software Development :: Build Tools
Classifier: Topic :: System :: Monitoring
Classifier: License :: OSI Approved :: MIT License
Classifier: Programming Language :: Python :: 3
Classifier: Programming Language :: Python :: 3.8
Classifier: Programming Language :: Python :: 3.9
Classifier: Programming Language :: Python :: 3.10
Classifier: Programming Language :: Python :: 3.11
Classifier: Programming Language :: Python :: 3.12
Classifier: Operating System :: OS Independent
Classifier: Environment :: Console
Requires-Python: >=3.8
License-File: LICENSE
Requires-Dist: requests>=2.28.0
Provides-Extra: dev
Requires-Dist: pytest>=7.0.0; extra == "dev"
Requires-Dist: pytest-cov>=4.0.0; extra == "dev"
Requires-Dist: black>=22.0.0; extra == "dev"
Requires-Dist: ruff>=0.1.0; extra == "dev"
Dynamic: author
Dynamic: home-page
Dynamic: license-file
Dynamic: platform
Dynamic: requires-python
